yaz_zichtgithub_plugin/__init__.py
yaz_zichtgithub_plugin/cache.py
yaz_zichtgithub_plugin/github.py
yaz_zichtgithub_plugin/log.py
yaz_zichtgithub_plugin/spreadsheet.py
yaz_zichtgithub_plugin/version.py
yaz_zichtgithub_plugin/zicht_dependency_matrix.py
yaz_zichtgithub_plugin/zicht_deployed_version.py
yaz_zichtgithub_plugin/zicht_github_finder.py
yaz_zichtgithub_plugin/zicht_repository_list.py
yaz_zichtgithub_plugin-0.5.12.data/scripts/yaz-zicht-dependency-matrix
yaz_zichtgithub_plugin-0.5.12.data/scripts/yaz-zicht-deployed-version
yaz_zichtgithub_plugin-0.5.12.data/scripts/yaz-zicht-github-finder
yaz_zichtgithub_plugin-0.5.12.data/scripts/yaz-zicht-repository-list
yaz_zichtgithub_plugin-0.5.12.dist-info/METADATA
yaz_zichtgithub_plugin-0.5.12.dist-info/WHEEL
yaz_zichtgithub_plugin-0.5.12.dist-info/top_level.txt
yaz_zichtgithub_plugin-0.5.12.dist-info/RECORD
