Metadata-Version: 2.1
Name: yaz-zichtgithub-plugin
Version: 0.5.12
Summary: A github plugin for YAZ
Home-page: http://github.com/yaz/yaz_zichtgithub_plugin
Author: Boudewijn Schoon
Author-email: yaz@frayja.nl
License: MIT
Platform: UNKNOWN
Classifier: Development Status :: 4 - Beta
Classifier: Environment :: Console
Classifier: License :: OSI Approved :: MIT License
Classifier: Programming Language :: Python :: 3.5
Classifier: Programming Language :: Python :: 3.6
Requires-Dist: yaz
Requires-Dist: pygithub
Requires-Dist: gspread
Requires-Dist: oauth2client
Requires-Dist: tabulate
